Metadata-Version: 1.0
Name: django-swiss-knife
Version: 0.1.9
Summary: A Django utils compilation.
Home-page: UNKNOWN
Author: Sthima
Author-email: eduardo@sthima.com.br
License: MIT
Platform: UNKNOWN
